testcli/__init__.py
testcli/apiparse.py
testcli/apivisitor.py
testcli/cmdexecute.py
testcli/cmdmapping.py
testcli/common.py
testcli/globalvar.py
testcli/hdfswrapper.py
testcli/helper.py
testcli/main.py
testcli/sqlclijdbc.py
testcli/sqlparse.py
testcli/sqlvisitor.py
testcli/testcli.py
testcli/testcliexception.py
testcli/testclijobmanager.py
testcli/testoption.py
testcli/antlrgen/APILexer.interp
testcli/antlrgen/APILexer.py
testcli/antlrgen/APILexer.tokens
testcli/antlrgen/APIParser.interp
testcli/antlrgen/APIParser.py
testcli/antlrgen/APIParser.tokens
testcli/antlrgen/APIParserVisitor.py
testcli/antlrgen/SQLLexer.interp
testcli/antlrgen/SQLLexer.py
testcli/antlrgen/SQLLexer.tokens
testcli/antlrgen/SQLParser.interp
testcli/antlrgen/SQLParser.py
testcli/antlrgen/SQLParser.tokens
testcli/antlrgen/SQLParserVisitor.py
testcli/antlrgen/__init__.py
testcli/commands/__init__.py
testcli/commands/assertExpression.py
testcli/commands/cliSleep.py
testcli/commands/compare.py
testcli/commands/connectdb.py
testcli/commands/data.py
testcli/commands/echo.py
testcli/commands/embeddScript.py
testcli/commands/exit.py
testcli/commands/helper.py
testcli/commands/host.py
testcli/commands/load.py
testcli/commands/session.py
testcli/commands/setOptions.py
testcli/commands/spool.py
testcli/commands/ssh.py
testcli/commands/start.py
testcli/commands/userNameSpace.py
testcli/commands/whenever.py
testcli/conf/testcli.ini
testcli/docs/UserGuide.md
testcli/jlib/h2-1.4.200.jar
testcli/profile/default
testcli/test/__init__.py
testcli/test/pytest.ini
testcli/test/testapiget.api
testcli/test/testapiget.ref
testcli/test/testapisynatx-get.api
testcli/test/testapisynatx-get.ref
testcli/test/testapisynatx-multipart.api
testcli/test/testapisynatx-multipart.ref
testcli/test/testcliunittest.py
testcli/test/testcompare.ref
testcli/test/testcompare.sql
testcli/test/testcompareref.txt
testcli/test/testcomparework.txt
testcli/test/testjobmanager.ref
testcli/test/testjobmanager.sql
robotslacker_testcli-0.1.1.dist-info/LICENSE.txt
robotslacker_testcli-0.1.1.dist-info/METADATA
robotslacker_testcli-0.1.1.dist-info/WHEEL
robotslacker_testcli-0.1.1.dist-info/entry_points.txt
robotslacker_testcli-0.1.1.dist-info/top_level.txt
robotslacker_testcli-0.1.1.dist-info/RECORD
