Metadata-Version: 2.1
Name: robotslacker-testcli
Version: 0.1.1
Summary: Test Command tool
Home-page: https://github.com/robotslacker/testcli.git
Author: RobotSlacker
Author-email: 184902652@qq.com
License: UNKNOWN
Keywords: test command sql api
Platform: any
Requires-Python: >=3.6
License-File: LICENSE.txt
Requires-Dist: JPype1
Requires-Dist: setproctitle
Requires-Dist: urllib3 (<1.27)
Requires-Dist: click
Requires-Dist: prompt-toolkit
Requires-Dist: paramiko
Requires-Dist: antlr4-python3-runtime
Requires-Dist: hdfs
Requires-Dist: fs
Requires-Dist: rich
Requires-Dist: pytest
Requires-Dist: fastapi
Requires-Dist: uvicorn
Requires-Dist: coloredlogs
Requires-Dist: robotframework
Requires-Dist: beautifulsoup4
Requires-Dist: lxml
